python_nbt/__init__.py
python_nbt/_util.py
python_nbt/nbt.py
Python_NBT-1.2.0.dist-info/LICENSE
Python_NBT-1.2.0.dist-info/METADATA
Python_NBT-1.2.0.dist-info/WHEEL
Python_NBT-1.2.0.dist-info/top_level.txt
Python_NBT-1.2.0.dist-info/RECORD
