Metadata-Version: 2.1
Name: Python-NBT
Version: 1.2.0
Summary: A python library for reading and writing NBT files
Home-page: https://github.com/TowardtheStars/Python-NBT
Author: TowardtheStars
Author-email: hty16@mail.ustc.edu.cn
License: GPLv3
Platform: UNKNOWN
Classifier: Development Status :: 4 - Beta
Classifier: Intended Audience :: Developers
Classifier: License :: OSI Approved :: GNU General Public License v3 (GPLv3)
Classifier: Operating System :: OS Independent
Classifier: Programming Language :: Python :: 3
Classifier: Topic :: Games/Entertainment
Classifier: Topic :: Software Development :: Libraries :: Python Modules
